dotcpp/DotCpp.Cpp.dll
dotcpp/__init__.py
dotcpp/dotcpp_ext.cp36-win_amd64.pyd
dotcpp/list_test.py
dotcpp-2.1.1.dist-info/LICENSE
dotcpp-2.1.1.dist-info/METADATA
dotcpp-2.1.1.dist-info/WHEEL
dotcpp-2.1.1.dist-info/top_level.txt
dotcpp-2.1.1.dist-info/RECORD
